<odoo>
  <data>
    <!-- explicit list view definition -->
    <!--
    <record model="ir.ui.view" id="weave.list">
      <field name="name">weave list</field>
      <field name="model">weave.weave</field>
      <field name="arch" type="xml">
        <tree>
          <field name="name"/>
          <field name="value"/>
          <field name="value2"/>
        </tree>
      </field>
    </record>
    -->

    <!-- actions opening views on models -->
    <!--
    <record model="ir.actions.act_window" id="weave.action_window">
      <field name="name">weave window</field>
      <field name="res_model">weave.weave</field>
      <field name="view_mode">tree,form</field>
    </record>
    -->

    <!-- server action to the one above -->
    <!--
    <record model="ir.actions.server" id="weave.action_server">
      <field name="name">weave server</field>
      <field name="model_id" ref="model_weave_weave"/>
      <field name="code">
        action = {
          "type": "ir.actions.act_window",
          "view_mode": "tree,form",
          "res_model": self._name,
        }
      </field>
    </record>
    -->

    <!-- Top menu item -->
    <!--
    <menuitem name="weave" id="weave.menu_root"/>
    -->
    <!-- menu categories -->
    <!--
    <menuitem name="Menu 1" id="weave.menu_1" parent="weave.menu_root"/>
    <menuitem name="Menu 2" id="weave.menu_2" parent="weave.menu_root"/>
    -->
    <!-- actions -->
    <!--
    <menuitem name="List" id="weave.menu_1_list" parent="weave.menu_1"
              action="weave.action_window"/>
    <menuitem name="Server to list" id="weave" parent="weave.menu_2"
              action="weave.action_server"/>
    -->
  </data>
</odoo>